textism/__init__.py
textism/textism.py
textism-1.0.dist-info/licenses/LICENSE.txt
textism-1.0.dist-info/METADATA
textism-1.0.dist-info/WHEEL
textism-1.0.dist-info/top_level.txt
textism-1.0.dist-info/RECORD
